memorizz/MEMORY_ARCHITECTURE.md
memorizz/__init__.py
memorizz/cli.py
memorizz/memagent.py
memorizz/memagent_original_backup.py
memorizz/multi_agent_orchestrator.py
memorizz/task_decomposition.py
memorizz/coordination/README.md
memorizz/coordination/__init__.py
memorizz/coordination/shared_memory/__init__.py
memorizz/coordination/shared_memory/messages.py
memorizz/coordination/shared_memory/shared_memory.py
memorizz/database/__init__.py
memorizz/database/mongodb/mongodb_tools.py
memorizz/embeddings/README.md
memorizz/embeddings/__init__.py
memorizz/embeddings/azure/__init__.py
memorizz/embeddings/azure/provider.py
memorizz/embeddings/huggingface/__init__.py
memorizz/embeddings/huggingface/provider.py
memorizz/embeddings/ollama/__init__.py
memorizz/embeddings/ollama/provider.py
memorizz/embeddings/openai/__init__.py
memorizz/embeddings/openai/provider.py
memorizz/embeddings/voyageai/__init__.py
memorizz/embeddings/voyageai/provider.py
memorizz/enums/__init__.py
memorizz/enums/application_mode.py
memorizz/enums/memory_type.py
memorizz/enums/role.py
memorizz/enums/semantic_cache_scope.py
memorizz/internet_access/__init__.py
memorizz/internet_access/base.py
memorizz/internet_access/models.py
memorizz/internet_access/providers/__init__.py
memorizz/internet_access/providers/firecrawl.py
memorizz/internet_access/providers/offline.py
memorizz/internet_access/providers/tavily.py
memorizz/llms/__init__.py
memorizz/llms/azure.py
memorizz/llms/huggingface.py
memorizz/llms/llm_factory.py
memorizz/llms/llm_provider.py
memorizz/llms/openai.py
memorizz/long_term_memory/__init__.py
memorizz/long_term_memory/episodic/README.md
memorizz/long_term_memory/episodic/__init__.py
memorizz/long_term_memory/episodic/conversational_memory_unit.py
memorizz/long_term_memory/episodic/summary_component.py
memorizz/long_term_memory/procedural/README.md
memorizz/long_term_memory/procedural/__init__.py
memorizz/long_term_memory/procedural/persona/README.md
memorizz-0.0.38.dist-info/METADATA
memorizz-0.0.38.dist-info/WHEEL
memorizz-0.0.38.dist-info/entry_points.txt
memorizz-0.0.38.dist-info/RECORD
