Metadata-Version: 2.4
Name: memorizz
Version: 0.0.38
Summary: A memory management library for Python
Author-email: Richmond Alake <richmond.alake@gmail.com>
License-Expression: MIT
Classifier: License :: OSI Approved :: MIT License
Classifier: Operating System :: OS Independent
Classifier: Programming Language :: Python :: 3
Requires-Python: >=3.7
Requires-Dist: accelerate>=0.26.0
Requires-Dist: numpy
Requires-Dist: openai
Requires-Dist: pydantic>=2.0.0
Requires-Dist: requests>=2.31.0
Requires-Dist: sentence-transformers>=2.5.0
Requires-Dist: transformers>=4.36.0
Provides-Extra: all
Requires-Dist: accelerate>=0.26.0; extra == 'all'
Requires-Dist: faiss-cpu>=1.7.4; extra == 'all'
Requires-Dist: langchain-ollama; extra == 'all'
Requires-Dist: numpy<2,>=1.21; extra == 'all'
Requires-Dist: ollama; extra == 'all'
Requires-Dist: oracledb>=2.0.0; extra == 'all'
Requires-Dist: pymongo>=4.0.0; extra == 'all'
Requires-Dist: sentence-transformers>=2.5.0; extra == 'all'
Requires-Dist: transformers>=4.36.0; extra == 'all'
Requires-Dist: voyageai; extra == 'all'
Provides-Extra: docs
Requires-Dist: mkdocs-git-revision-date-localized-plugin>=1.2.0; extra == 'docs'
Requires-Dist: mkdocs-material>=9.5.0; extra == 'docs'
Requires-Dist: mkdocs>=1.6.0; extra == 'docs'
Requires-Dist: mkdocstrings[python]>=0.24.0; extra == 'docs'
Requires-Dist: pymdown-extensions>=10.0; extra == 'docs'
Provides-Extra: filesystem
Requires-Dist: faiss-cpu>=1.7.4; extra == 'filesystem'
Provides-Extra: huggingface
Requires-Dist: accelerate>=0.26.0; extra == 'huggingface'
Requires-Dist: numpy<2,>=1.21; extra == 'huggingface'
Requires-Dist: sentence-transformers>=2.5.0; extra == 'huggingface'
Requires-Dist: transformers>=4.36.0; extra == 'huggingface'
Provides-Extra: mongodb
Requires-Dist: pymongo>=4.0.0; extra == 'mongodb'
Provides-Extra: ollama
Requires-Dist: langchain-ollama; extra == 'ollama'
Requires-Dist: ollama; extra == 'ollama'
Provides-Extra: oracle
Requires-Dist: oracledb>=2.0.0; extra == 'oracle'
Provides-Extra: voyageai
Requires-Dist: voyageai; extra == 'voyageai'
